OTU_predictor/OTU_predictor.py
OTU_predictor/__init__.py
otu_predictor-1.1.0.dist-info/METADATA
otu_predictor-1.1.0.dist-info/WHEEL
otu_predictor-1.1.0.dist-info/top_level.txt
otu_predictor-1.1.0.dist-info/RECORD
