Metadata-Version: 2.4
Name: OTU_predictor
Version: 1.1.0
Summary: Uses a randomForest model to predict which OTUs are present in a microbiome
Author: Andrew Tedder
Author-email: Andrew Tedder <a.tedder@bradford.ac.uk>
License: MIT
Project-URL: Homepage, https://github.com/atedder/OTU_predictor
Project-URL: Source, https://github.com/atedder/OTU_predictor
Project-URL: Tracker, https://github.com/atedder/OTU_predictor/issues
Keywords: microbiome,random forest,OTU prediction,machine learning,bioinformatics
Classifier: Programming Language :: Python :: 3
Classifier: Programming Language :: Python :: 3.8
Classifier: Programming Language :: Python :: 3.9
Classifier: Programming Language :: Python :: 3.10
Classifier: License :: OSI Approved :: MIT License
Classifier: Operating System :: OS Independent
Classifier: Topic :: Scientific/Engineering :: Bio-Informatics
Classifier: Topic :: Software Development :: Libraries
Requires-Python: >=3.8
Requires-Dist: scikit-learn
Requires-Dist: numpy
Requires-Dist: pandas
Requires-Dist: joblib
Dynamic: author
Dynamic: requires-python
